funlbm/__init__.py
funlbm/analyse/__init__.py
funlbm/base/__init__.py
funlbm/base/work.py
funlbm/config/__init__.py
funlbm/config/base.py
funlbm/file/__init__.py
funlbm/file/wrap.py
funlbm/file/tecplot/__init__.py
funlbm/file/tecplot/dump.py
funlbm/file/vtk/dump.py
funlbm/flow/__init__.py
funlbm/flow/base.py
funlbm/flow/d3/__init__.py
funlbm/flow/d3/base.py
funlbm/flow/d3/d3q13.py
funlbm/flow/d3/d3q15.py
funlbm/flow/d3/d3q19.py
funlbm/flow/d3/d3q27.py
funlbm/lbm/__init__.py
funlbm/lbm/base.py
funlbm/lbm/lbm3d.py
funlbm/particle/__init__.py
funlbm/particle/coord.py
funlbm/particle/swarm.py
funlbm/particle/base/__init__.py
funlbm/particle/base/base.py
funlbm/particle/base/ellipsoid.py
funlbm/particle/base/sphere.py
funlbm/particle/base/spheroid.py
funlbm/plot/__init__.py
funlbm/plot/dump.py
funlbm/plot/job.py
funlbm/server/__init__.py
funlbm/server/base.py
funlbm/server/run.py
funlbm/server/submit.py
funlbm/server/update.py
funlbm/util/__init__.py
funlbm/util/env.py
funlbm/util/format.py
funlbm/util/log.py
funlbm-1.2.53.dist-info/METADATA
funlbm-1.2.53.dist-info/WHEEL
funlbm-1.2.53.dist-info/entry_points.txt
funlbm-1.2.53.dist-info/top_level.txt
funlbm-1.2.53.dist-info/RECORD
