Metadata-Version: 2.4
Name: funlbm
Version: 1.2.53
Summary: funlbm
Author-email: 牛哥 <niuliangtao@qq.com>, farfarfun <farfarfun@qq.com>
Maintainer-email: 牛哥 <niuliangtao@qq.com>, farfarfun <farfarfun@qq.com>
Project-URL: Organization, https://github.com/farfarfun
Project-URL: Repository, https://github.com/farfarfun/funlbm
Project-URL: Releases, https://github.com/farfarfun/funlbm/releases
Requires-Python: >=3.9
Requires-Dist: funtable>=1.0.25
Requires-Dist: funtecplot>=1.0.1
Requires-Dist: funutil>=1.0.14
Requires-Dist: funvtk>=1.0.9
Requires-Dist: h5py>=3.13.0
Requires-Dist: nicegui>=2.15.0
Requires-Dist: pandas>=2.2.3
Requires-Dist: scipy>=1.13.1
Requires-Dist: tinydb>=4.8.2
Requires-Dist: torch>=2.2.0
Requires-Dist: transforms3d>=0.4.2
Requires-Dist: typer>=0.15.2
